{
	"configurations" : 
	[
		{
			"directories" : 
			[
				{
					"build" : ".",
					"hasInstallRule" : true,
					"jsonFile" : "directory-.-af751ff61593ac050c91.json",
					"minimumCMakeVersion" : 
					{
						"string" : "3.12"
					},
					"projectIndex" : 0,
					"source" : ".",
					"targetIndexes" : 
					[
						0,
						1,
						2
					]
				}
			],
			"name" : "",
			"projects" : 
			[
				{
					"directoryIndexes" : 
					[
						0
					],
					"name" : "nav_sim",
					"targetIndexes" : 
					[
						0,
						1,
						2
					]
				}
			],
			"targets" : 
			[
				{
					"directoryIndex" : 0,
					"id" : "NAV_cmd::@6890427a1f51a3e7e1df",
					"jsonFile" : "target-NAV_cmd-dfd705ff76a3b93d7311.json",
					"name" : "NAV_cmd",
					"projectIndex" : 0
				},
				{
					"directoryIndex" : 0,
					"id" : "nav_sim_uninstall::@6890427a1f51a3e7e1df",
					"jsonFile" : "target-nav_sim_uninstall-7fa8a10067e28cf30d14.json",
					"name" : "nav_sim_uninstall",
					"projectIndex" : 0
				},
				{
					"directoryIndex" : 0,
					"id" : "uninstall::@6890427a1f51a3e7e1df",
					"jsonFile" : "target-uninstall-b5c066849776022eb29a.json",
					"name" : "uninstall",
					"projectIndex" : 0
				}
			]
		}
	],
	"kind" : "codemodel",
	"paths" : 
	{
		"build" : "/home/nvidia/MotorcarV1.1_ws/build/nav_sim",
		"source" : "/home/nvidia/MotorcarV1.1_ws/src/nav_sim"
	},
	"version" : 
	{
		"major" : 2,
		"minor" : 3
	}
}
